plummy/__init__.py
plummy/adapters.py
plummy/handlers.py
plummy/protocols.py
plummy-0.1.1.dist-info/WHEEL
plummy-0.1.1.dist-info/entry_points.txt
plummy-0.1.1.dist-info/METADATA
plummy-0.1.1.dist-info/RECORD
