Metadata-Version: 2.3
Name: plummy
Version: 0.1.1
Summary: Add your description here
Author: GuillermoLB
Author-email: GuillermoLB <guillelb99@gmail.com>
Requires-Dist: pydantic>=2.0.0
Requires-Dist: ruff>=0.14.0 ; extra == 'dev'
Requires-Dist: pytest>=7.0.0 ; extra == 'dev'
Requires-Dist: pytest-mock>=3.0.0 ; extra == 'dev'
Requires-Dist: pytest-cov>=4.0.0 ; extra == 'dev'
Requires-Python: >=3.12
Provides-Extra: dev
